errata/__init__.py
errata/main.py
errata-0.1.0.dist-info/WHEEL
errata-0.1.0.dist-info/entry_points.txt
errata-0.1.0.dist-info/METADATA
errata-0.1.0.dist-info/RECORD
